COPYING
MANIFEST.in
README.md
RELEASE-VERSION
SConstruct
pavement.py
paver-minilib.zip
setup.py
version.py
open_drop/Untitled0.ipynb
open_drop/__init__.py
open_drop/config.py
open_drop/node.py
open_drop/proxy.py
open_drop.egg-info/PKG-INFO
open_drop.egg-info/SOURCES.txt
open_drop.egg-info/dependency_links.txt
open_drop.egg-info/pbr.json
open_drop.egg-info/requires.txt
open_drop.egg-info/top_level.txt
open_drop/Arduino/library/OpenDrop/CommandProcessor.h
open_drop/Arduino/library/OpenDrop/Commands.h
open_drop/Arduino/library/OpenDrop/Properties.h
open_drop/Arduino/library/OpenDrop/config_pb.c
open_drop/Arduino/library/OpenDrop/config_pb.h
open_drop/Arduino/open_drop/Node.cpp
open_drop/Arduino/open_drop/Node.h
open_drop/Arduino/open_drop/NodeCommandProcessor.h
open_drop/Arduino/open_drop/RPCBuffer.h
open_drop/Arduino/open_drop/RPCBuffer.h.bak
open_drop/Arduino/open_drop/RPCBuffer.ht
open_drop/Arduino/open_drop/SConscript
open_drop/Arduino/open_drop/config.options
open_drop/Arduino/open_drop/config.proto
open_drop/Arduino/open_drop/open_drop.ino
open_drop/Arduino/open_drop/open_drop_config_validate.h
open_drop/Arduino/open_drop/open_drop_config_validate.h.bak
open_drop/Arduino/open_drop/open_drop_state_validate.h
open_drop/Arduino/open_drop/open_drop_state_validate.h.bak
open_drop/bin/__init__.py
open_drop/bin/upload.py
open_drop/firmware/mega2560/open_drop.hex
open_drop/firmware/uno/open_drop.hex