Metadata-Version: 1.0
Name: open-drop
Version: 0.2.post17
Summary: Arduino RPC node packaged as Python package.
Home-page: http://github.com/wheeler-microfluidics/open-drop.git
Author: Christian Fobel
Author-email: christian@fobel.net
License: GPLv2
Platform: UNKNOWN
